latch_data_validation/__init__.py
latch_data_validation/data_validation.py
latch_data_validation/py.typed
latch_data_validation-0.1.12.dist-info/METADATA
latch_data_validation-0.1.12.dist-info/WHEEL
latch_data_validation-0.1.12.dist-info/licenses/LICENSE
latch_data_validation-0.1.12.dist-info/RECORD
