Metadata-Version: 2.4
Name: latch-data-validation
Version: 0.1.12
Summary: Runtime type validation
Author-email: maximsmol <max@latch.bio>
License: CC0-1.0
License-File: LICENSE
Requires-Python: >=3.11.0
Requires-Dist: opentelemetry-api>=1.15.0
